sphinxarg/__init__.py
sphinxarg/ext.py
sphinxarg/markdown.py
sphinxarg/parser.py
sphinx_argparse-0.5.1.dist-info/WHEEL
sphinx_argparse-0.5.1.dist-info/METADATA
sphinx_argparse-0.5.1.dist-info/RECORD
